seam_nrp/__init__.py
seam_nrp/demo.py
seam_nrp-0.1.0.dist-info/METADATA
seam_nrp-0.1.0.dist-info/WHEEL
seam_nrp-0.1.0.dist-info/entry_points.txt
seam_nrp-0.1.0.dist-info/top_level.txt
seam_nrp-0.1.0.dist-info/RECORD
